swiftgalaxy/__init__.py
swiftgalaxy/__version__.py
swiftgalaxy/demo_data.py
swiftgalaxy/halo_catalogues.py
swiftgalaxy/iterator.py
swiftgalaxy/masks.py
swiftgalaxy/reader.py
swiftgalaxy/json/caesar_unit_registry.json
swiftgalaxy-2.3.2.dist-info/licenses/LICENSE.md
swiftgalaxy-2.3.2.dist-info/METADATA
swiftgalaxy-2.3.2.dist-info/WHEEL
swiftgalaxy-2.3.2.dist-info/top_level.txt
swiftgalaxy-2.3.2.dist-info/RECORD
