Metadata-Version: 2.4
Name: swiftgalaxy
Version: 2.3.2
Summary: Code abstraction of objects (galaxies) in simulations.
Author-email: Kyle Oman <kyle.a.oman@durham.ac.uk>
License-Expression: GPL-3.0-or-later
Project-URL: Homepage, https://github.com/SWIFTSIM/swiftgalaxy
Project-URL: Bug Tracker, https://github.com/SWIFTSIM/swiftgalaxy/issues
Project-URL: Documentation, https://swiftgalaxy.readthedocs.io/en/latest
Classifier: Programming Language :: Python :: 3
Classifier: Operating System :: OS Independent
Requires-Python: >=3.10
License-File: LICENSE.md
Requires-Dist: numpy
Requires-Dist: scipy
Requires-Dist: unyt
Requires-Dist: swiftsimio>=10.0.0
Requires-Dist: requests
Provides-Extra: extra
Requires-Dist: tqdm; extra == "extra"
Requires-Dist: astropy; extra == "extra"
Provides-Extra: velociraptor
Requires-Dist: velociraptor; extra == "velociraptor"
Provides-Extra: all
Requires-Dist: swiftgalaxy[extra,velociraptor]; extra == "all"
Provides-Extra: testing
Requires-Dist: pytest; extra == "testing"
Requires-Dist: pytest-xdist; extra == "testing"
Requires-Dist: pytest-cov; extra == "testing"
Requires-Dist: flake8; extra == "testing"
Requires-Dist: ruff; extra == "testing"
Requires-Dist: mypy; extra == "testing"
Requires-Dist: numpydoc; extra == "testing"
Requires-Dist: nbmake; extra == "testing"
Requires-Dist: sphinx-lint; extra == "testing"
Provides-Extra: docs
Requires-Dist: sphinx; extra == "docs"
Requires-Dist: sphinx-rtd-theme; extra == "docs"
Requires-Dist: sphinx-design; extra == "docs"
Requires-Dist: recommonmark; extra == "docs"
Provides-Extra: dev
Requires-Dist: swiftgalaxy[all,docs,testing]; extra == "dev"
Dynamic: license-file
